mongo_connector/__init__.py
mongo_connector/doc_managers/__init__.py
mongo_connector/doc_managers/elastic2_doc_manager.py
elastic2_doc_manager-1.0.0.dist-info/LICENSE
elastic2_doc_manager-1.0.0.dist-info/METADATA
elastic2_doc_manager-1.0.0.dist-info/WHEEL
elastic2_doc_manager-1.0.0.dist-info/top_level.txt
elastic2_doc_manager-1.0.0.dist-info/RECORD
