Metadata-Version: 2.1
Name: elastic2-doc-manager
Version: 1.0.0
Summary: Elastic2 plugin for mongo-connector
Home-page: https://github.com/mongodb-labs/elastic2-doc-manager
Author: anna herlihy
Author-email: mongodb-user@googlegroups.com
Maintainer: mongodb
License: UNKNOWN
Keywords: mongo-connector,mongodb,elastic,elasticsearch
Platform: any
Classifier: Development Status :: 4 - Beta
Classifier: Intended Audience :: Developers
Classifier: License :: OSI Approved :: Apache Software License
Classifier: Programming Language :: Python :: 3
Classifier: Topic :: Database
Classifier: Topic :: Software Development :: Libraries :: Python Modules
Classifier: Operating System :: Unix
Classifier: Operating System :: MacOS :: MacOS X
Classifier: Operating System :: Microsoft :: Windows
Classifier: Operating System :: POSIX
Requires-Python: >=3.4
Requires-Dist: mongo-connector (>=2.5.0)
Requires-Dist: importlib-metadata
Provides-Extra: aws
Requires-Dist: boto3 (>=1.4.0); extra == 'aws'
Requires-Dist: requests-aws-sign (>=0.1.2); extra == 'aws'
Provides-Extra: elastic2
Requires-Dist: elasticsearch (<3.0.0,>=2.0.0); extra == 'elastic2'
Provides-Extra: elastic5
Requires-Dist: elasticsearch (<6.0.0,>=5.0.0); extra == 'elastic5'
